xdocument/__init__.py
xdocument/__init__.pyi
xdocument/py.typed
xdocument/xdocument.py
xdocument/xdocument.pyi
xdocument-1.3.2.dist-info/licenses/LICENSE
xdocument-1.3.2.dist-info/METADATA
xdocument-1.3.2.dist-info/WHEEL
xdocument-1.3.2.dist-info/top_level.txt
xdocument-1.3.2.dist-info/RECORD
