Metadata-Version: 2.4
Name: xdocument
Version: 1.3.2
Summary: A high-level abstraction layer for creating and editing XML documents.
Author-email: John Bolkcom <johnbolk6502@gmail.com>
License-Expression: MIT
Project-URL: Homepage, https://github.com/johnbolk/xdocument.git
Keywords: XML,DOM
Classifier: Programming Language :: Python :: 3
Classifier: Operating System :: OS Independent
Classifier: Intended Audience :: Developers
Requires-Python: >=3.7
License-File: LICENSE
Requires-Dist: defusedxml>=0.7.1
Dynamic: license-file
